{
   "antivirusEngine":{
    "exclusions":[
        // core paths, files, process
        {
           "$type":"excludedPath",
           "isDirectory":true,
           "path":"/opt/Tanium/TaniumClient/*/"
        },
        {
            "$type":"excludedFileName",
            "name":"/opt/Tanium/TaniumClient/Tools/StdUtils/TaniumExecWrapper"
        },
        {
            "$type":"excludedFileName",
            "name":"/opt/Tanium/TaniumClient/Tools/StdUtils/distribute-tools.sh"
        },
        {
            "$type":"excludedFileName",
            "name":"/opt/Tanium/TaniumClient/TaniumClient"
        },
        {
            "$type":"excludedFileName",
            "name":"/opt/Tanium/TaniumClient/taniumclient"
        },
        {
            "$type":"excludedFileName",
            "name":"/opt/Tanium/TaniumClient/TaniumCX"
        },
        // Solution Asset
        {
            "$type":"excludedFileName",
            "name":"/opt/Tanium/TaniumClient/Tools/EPI/TaniumEndpointIndex"
        },   
        {
            "$type":"excludedFileName",
            "name":"/opt/Tanium/TaniumClient/Tools/Asset/TaniumFileEvidence"
        },
        {
            "$type":"excludedPath",
            "isDirectory":false,
            "path":"/opt/Tanium/TaniumClient/extensions/libTaniumSoftwareManager.so"
        },
        {
            "$type":"excludedPath",
            "isDirectory":false,
            "path":"/opt/Tanium/TaniumClient/extensions/libTaniumSoftwareManager.so.sig"
        },
        {
            "$type":"excludedPath",
            "isDirectory":false,
            "path":"/opt/Tanium/TaniumClient/libTaniumClientExtensions.so"
        },
        {
            "$type":"excludedPath",
            "isDirectory":false,
            "path":"/opt/Tanium/TaniumClient/libTaniumClientExtensions.so.sig"
        },
        {
            "$type":"excludedPath",
            "isDirectory":false,
            "path":"/opt/Tanium/TaniumClient/extensions/libSupportCX.so"
        },
        {
            "$type":"excludedPath",
            "isDirectory":false,
            "path":"/opt/Tanium/TaniumClient/extensions/libSupportCX.so.sig"
        },
        {
            "$type":"excludedPath",
            "isDirectory":false,
            "path":"/opt/Tanium/TaniumClient/extensions/libTaniumConfig.so"
        },
        {
            "$type":"excludedPath",
            "isDirectory":false,
            "path":"/opt/Tanium/TaniumClient/extensions/libTaniumConfig.so.sig"
        }
     ],
      "enforcementLevel":"real_time",
      "threatTypeSettings":[
         {
            "key":"potentially_unwanted_application",
            "value":"block"
         },
         {
            "key":"archive_bomb",
            "value":"audit"
         }
      ]
   },
   "cloudService":{
      "enabled":true,
      "automaticSampleSubmissionConsent":"safe",
      "automaticDefinitionUpdateEnabled":true
   }
}